odoo/addons/project_task_sign_oca/README.rst
odoo/addons/project_task_sign_oca/__init__.py
odoo/addons/project_task_sign_oca/__manifest__.py
odoo/addons/project_task_sign_oca/demo/sign_oca_role.xml
odoo/addons/project_task_sign_oca/demo/sign_oca_template.xml
odoo/addons/project_task_sign_oca/i18n/ca_ES.po
odoo/addons/project_task_sign_oca/i18n/it.po
odoo/addons/project_task_sign_oca/i18n/project_task_sign_oca.pot
odoo/addons/project_task_sign_oca/models/__init__.py
odoo/addons/project_task_sign_oca/models/project_task.py
odoo/addons/project_task_sign_oca/models/res_company.py
odoo/addons/project_task_sign_oca/models/res_config_settings.py
odoo/addons/project_task_sign_oca/models/sign_oca_request.py
odoo/addons/project_task_sign_oca/readme/CONFIGURE.md
odoo/addons/project_task_sign_oca/readme/CONTRIBUTORS.md
odoo/addons/project_task_sign_oca/readme/DESCRIPTION.md
odoo/addons/project_task_sign_oca/readme/USAGE.md
odoo/addons/project_task_sign_oca/static/description/icon.png
odoo/addons/project_task_sign_oca/static/description/index.html
odoo/addons/project_task_sign_oca/tests/__init__.py
odoo/addons/project_task_sign_oca/tests/test_project_task_sign_oca.py
odoo/addons/project_task_sign_oca/views/project_task.xml
odoo/addons/project_task_sign_oca/views/res_config_settings.xml
odoo/addons/project_task_sign_oca/views/sign_oca_request.xml
odoo_addon_project_task_sign_oca-18.0.1.0.0.2.dist-info/METADATA
odoo_addon_project_task_sign_oca-18.0.1.0.0.2.dist-info/WHEEL
odoo_addon_project_task_sign_oca-18.0.1.0.0.2.dist-info/top_level.txt
odoo_addon_project_task_sign_oca-18.0.1.0.0.2.dist-info/RECORD
